datasette_copyable/__init__.py
datasette_copyable/templates/copyable.html
datasette_copyable-0.3.2.dist-info/METADATA
datasette_copyable-0.3.2.dist-info/WHEEL
datasette_copyable-0.3.2.dist-info/entry_points.txt
datasette_copyable-0.3.2.dist-info/top_level.txt
datasette_copyable-0.3.2.dist-info/RECORD
