Metadata-Version: 2.1
Name: datasette-copyable
Version: 0.3.2
Summary: Datasette plugin for outputting tables in formats suitable for copy and paste
Home-page: https://github.com/simonw/datasette-copyable
Author: Simon Willison
License: Apache License, Version 2.0
Project-URL: Issues, https://github.com/simonw/datasette-copyable/issues
Project-URL: CI, https://github.com/simonw/datasette-copyable/actions
Project-URL: Changelog, https://github.com/simonw/datasette-copyable/releases
Requires-Python: >=3.7
Requires-Dist: datasette (>=0.63)
Requires-Dist: tabulate
Provides-Extra: test
Requires-Dist: pytest ; extra == 'test'
Requires-Dist: pytest-asyncio ; extra == 'test'
Requires-Dist: httpx ; extra == 'test'
Requires-Dist: sqlite-utils ; extra == 'test'
